{
  "id": "third-person",
  "name": "ThirdPerson",
  "author": "Rick6",
  "description": "Allows any player with permission to use third-person view.",
  "categories": [
    "rust"
  ],
  "total_downloads": 20278,
  "latest_version": "0.1.5",
  "created_at": "2018-08-02T18:51:48",
  "updated_at": "2025-03-21T11:10:30",
  "versions": [
    {
      "version": "0.1.5",
      "released_at": "2025-03-24T00:17:17.537408",
      "download_url": "https://umod.org/plugins/third-person/download/latest",
      "changelog": null
    }
  ]
}