{
  "id": "limit-rcon",
  "name": "LimitRCON",
  "author": "Lorenc",
  "description": "Limits RCON access to specific IP addresses",
  "categories": [
    "rust"
  ],
  "total_downloads": 8691,
  "latest_version": "1.0.0",
  "created_at": "2018-08-02T18:50:12",
  "updated_at": "2025-03-21T18:42:42",
  "versions": [
    {
      "version": "1.0.0",
      "released_at": "2025-03-23T23:48:33.348034",
      "download_url": "https://umod.org/plugins/limit-rcon/download/latest",
      "changelog": null
    }
  ]
}