{
  "id": "the-purge",
  "name": "Purge",
  "author": "MrBlue",
  "description": "Allows damage and killing only between specified hours",
  "categories": [
    "rust"
  ],
  "total_downloads": 15431,
  "latest_version": "1.2.2",
  "created_at": "2018-08-02T18:42:07",
  "updated_at": "2025-03-14T09:14:09",
  "versions": [
    {
      "version": "1.2.2",
      "released_at": "2025-03-24T00:17:03.601039",
      "download_url": "https://umod.org/plugins/the-purge/download/latest",
      "changelog": null
    }
  ]
}