{
  "id": "wipe-kits",
  "name": "WipeKits",
  "author": "Ryan",
  "description": "Puts a configurable cooldown from the wipe on each kit based on kit name",
  "categories": [
    "rust"
  ],
  "total_downloads": 38799,
  "latest_version": "1.2.52",
  "created_at": "2018-07-24T21:35:24",
  "updated_at": "2025-03-23T06:23:12",
  "versions": [
    {
      "version": "1.2.52",
      "released_at": "2025-03-24T00:23:02.162982",
      "download_url": "https://umod.org/plugins/wipe-kits/download/latest",
      "changelog": null
    }
  ]
}