{
  "id": "community-vigilance",
  "name": "CommunityVigilance",
  "author": "PinguinNordpol",
  "description": "Start a vote to kick someone from the server",
  "categories": [
    "rust"
  ],
  "total_downloads": 1876,
  "latest_version": "0.2.2",
  "created_at": "2021-04-13T20:17:55",
  "updated_at": "2025-03-20T12:31:31",
  "versions": [
    {
      "version": "0.2.2",
      "released_at": "2025-03-23T23:28:26.129987",
      "download_url": "https://umod.org/plugins/community-vigilance/download/latest",
      "changelog": null
    }
  ]
}