{
  "id": "waterless-sprinklers",
  "name": "WaterlessSprinklers",
  "author": "Lorenzo",
  "description": "Sprinklers will run without water pipe connection.",
  "categories": [
    "rust"
  ],
  "total_downloads": 14480,
  "latest_version": "1.0.3",
  "created_at": "2021-10-05T18:11:59",
  "updated_at": "2025-03-22T18:29:13",
  "versions": [
    {
      "version": "1.0.3",
      "released_at": "2025-03-24T00:22:09.295466",
      "download_url": "https://umod.org/plugins/waterless-sprinklers/download/latest",
      "changelog": null
    }
  ]
}